odoo10_addon_l10n_br_zip-10.0.1.0.0.99.dev12-nspkg.pth
odoo/addons/l10n_br_zip/README.rst
odoo/addons/l10n_br_zip/__init__.py
odoo/addons/l10n_br_zip/__manifest__.py
odoo/addons/l10n_br_zip/demo/l10n_br_zip_demo.xml
odoo/addons/l10n_br_zip/i18n/l10n_br_zip.pot
odoo/addons/l10n_br_zip/models/__init__.py
odoo/addons/l10n_br_zip/models/l10n_br_zip.py
odoo/addons/l10n_br_zip/models/res_bank.py
odoo/addons/l10n_br_zip/models/res_company.py
odoo/addons/l10n_br_zip/models/res_partner.py
odoo/addons/l10n_br_zip/security/ir.model.access.csv
odoo/addons/l10n_br_zip/static/description/icon.png
odoo/addons/l10n_br_zip/tests/__init__.py
odoo/addons/l10n_br_zip/tests/test_l10n_br_zip.py
odoo/addons/l10n_br_zip/views/l10n_br_zip_view.xml
odoo/addons/l10n_br_zip/views/res_bank_view.xml
odoo/addons/l10n_br_zip/views/res_company_view.xml
odoo/addons/l10n_br_zip/views/res_partner_view.xml
odoo/addons/l10n_br_zip/wizard/__init__.py
odoo/addons/l10n_br_zip/wizard/l10n_br_zip_search.py
odoo/addons/l10n_br_zip/wizard/l10n_br_zip_search_view.xml
odoo10_addon_l10n_br_zip-10.0.1.0.0.99.dev12.dist-info/METADATA
odoo10_addon_l10n_br_zip-10.0.1.0.0.99.dev12.dist-info/WHEEL
odoo10_addon_l10n_br_zip-10.0.1.0.0.99.dev12.dist-info/namespace_packages.txt
odoo10_addon_l10n_br_zip-10.0.1.0.0.99.dev12.dist-info/top_level.txt
odoo10_addon_l10n_br_zip-10.0.1.0.0.99.dev12.dist-info/RECORD
